dotfilesmgmt/__init__.py
dotfilesmgmt/dotfilesmgmt.py
dotfilesmgmt-0.0.6.dist-info/METADATA
dotfilesmgmt-0.0.6.dist-info/WHEEL
dotfilesmgmt-0.0.6.dist-info/entry_points.txt
dotfilesmgmt-0.0.6.dist-info/licenses/LICENSE
dotfilesmgmt-0.0.6.dist-info/RECORD
