Metadata-Version: 2.3
Name: dotfilesmgmt
Version: 0.0.6
Summary: Using Python virtual env and providing GIT_DIR, GIT_WORK_TREE environment variable for Git to manage dotfiles.
Project-URL: Homepage, https://github.com/YuKangjie/dotfilesmgmt
Project-URL: Issues, https://github.com/YuKangjie/dotfilesmgmt/issues
Author: Kangjie YU
License-File: LICENSE
Classifier: License :: OSI Approved :: MIT License
Classifier: Operating System :: Microsoft :: Windows
Classifier: Operating System :: POSIX :: Linux
Classifier: Programming Language :: Python :: 3
Requires-Python: >=3.8
